pyams/PyAMS.py
pyams/SymbolEditor.py
pyams/__init__.py
pyams/cad/PythonEditor.py
pyams/cad/__init__.py
pyams/cad/about.py
pyams/cad/appcir.py
pyams/cad/config.py
pyams/cad/data_rc.py
pyams/cad/description.py
pyams/cad/dialogLibraryManagement.py
pyams/cad/dialogListParams.py
pyams/cad/dialogListSignalsParamatersNets.py
pyams/cad/dialogProcessInterface.py
pyams/cad/dialogs.py
pyams/cad/file_history.json
pyams/cad/file_history_sym.json
pyams/cad/findModel.py
pyams/cad/graphDescription.py
pyams/cad/mainwindow.py
pyams/cad/mainwindow.ui
pyams/cad/showGraph.py
pyams/cad/showGraph.ui
pyams/cad/synedit.py
pyams/data/data.qrc
pyams/data/index.html
pyams/data/ioData.js
pyams/data/ioQt.js
pyams/data/note.js
pyams/data/plotly-latest.min.js
pyams/data/qwebchannel.js
pyams/data/showGraph.html
pyams/data/split.js
pyams/data/std.js
pyams/data/image/ACAnalysis.png
pyams/data/image/AV.png
pyams/data/image/AddArc.png
pyams/data/image/AddEllipse.png
pyams/data/image/AddImage.png
pyams/data/image/AddParamater.png
pyams/data/image/AddPart.png
pyams/data/image/AddPie.png
pyams/data/image/AddPin.png
pyams/data/image/AddPolygon.png
pyams/data/image/AddPolyline.png
pyams/data/image/AddRect.png
pyams/data/image/AddRef.png
pyams/data/image/AddText.png
pyams/data/image/Addparam.png
pyams/data/image/Analysis.png
pyams/data/image/Copy.png
pyams/data/image/CreatParts_Icon.ico
pyams/data/image/Cut.png
pyams/data/image/DCAnalysis.png
pyams/data/image/End.ico
pyams/data/image/End.png
pyams/data/image/FlipHorizontal.png
pyams/data/image/FlipVertically.png
pyams/data/image/Html.png
pyams/data/image/Label.png
pyams/data/image/New.png
pyams/data/image/Open.png
pyams/data/image/Redo.png
pyams/data/image/Rotate.png
pyams/data/image/RoundRect.png
pyams/data/image/Run.png
pyams/data/image/RunAnalysis.png
pyams/data/image/Save.png
pyams/data/image/TRAnalysis.png
pyams/data/image/Undo.png
pyams/data/image/Zomm_100.png
pyams/data/image/Zoom In.png
pyams/data/image/Zoom Out.png
pyams/data/image/after.png
pyams_cad-0.1.4.1.dist-info/licenses/LICENSE
pyams_cad-0.1.4.1.dist-info/METADATA
pyams_cad-0.1.4.1.dist-info/WHEEL
pyams_cad-0.1.4.1.dist-info/top_level.txt
pyams_cad-0.1.4.1.dist-info/RECORD
