Metadata-Version: 2.4
Name: pyams_cad
Version: 0.1.4.1
Summary: Design and simulation of circuits and modeling of analog and mixed-signal electronic components using CAD systems.
Home-page: https://pyams.sf.net/
Author: Dhiabi.Fathi
Author-email: dhiabi.fathi@gmail.com
Project-URL: Source, https://github.com/d-fathi/pyams
Project-URL: Documentation, https://pyams.sf.net/doc
Project-URL: Bug Tracker, https://github.com/d-fathi/pyams/issues
Keywords: simulation,circuit,electronics,mixed-signal,analog,EDA,electronic modeling,electrical engineering
Classifier: Development Status :: 4 - Beta
Classifier: Intended Audience :: Science/Research
Classifier: Intended Audience :: Developers
Classifier: Topic :: Scientific/Engineering :: Electronic Design Automation (EDA)
Classifier: License :: OSI Approved :: GNU General Public License v3 (GPLv3)
Classifier: Programming Language :: Python :: 3
Classifier: Operating System :: OS Independent
Requires-Python: >=3.6
License-File: LICENSE
Requires-Dist: PyQt5
Requires-Dist: PyQtWebEngine
Dynamic: author
Dynamic: author-email
Dynamic: classifier
Dynamic: description
Dynamic: description-content-type
Dynamic: home-page
Dynamic: keywords
Dynamic: license-file
Dynamic: project-url
Dynamic: requires-dist
Dynamic: requires-python
Dynamic: summary
